{
  "project_info": {
    "project_number": "664808646303",
    "project_id": "overrun-d5c38",
    "storage_bucket": "overrun-d5c38.firebasestorage.app"
  },
  "client": [
    {
      "client_info": {
        "mobilesdk_app_id": "1:664808646303:android:29fefc9f28ed74fb2b64aa",
        "android_client_info": {
          "package_name": "com.example.overrun"
        }
      },
      "oauth_client": [],
      "api_key": [
        {
          "current_key": "AIzaSyAaCP5a7ixhy5nVw9MvNc06ErRl4w1RIIM"
        }
      ],
      "services": {
        "appinvite_service": {
          "other_platform_oauth_client": []
        }
      }
    }
  ],
  "configuration_version": "1"
}